[{"id":165,"votos":2,"candidato":"Paul Carrasco","value":0.06},{"id":480,"votos":30,"candidato":"Paul Carrasco","value":0.34},{"id":2600,"votos":10,"candidato":"Paul Carrasco","value":0.22},{"id":2635,"votos":3,"candidato":"Paul Carrasco","value":0.17},{"id":3735,"votos":3,"candidato":"Paul Carrasco","value":0.12},{"id":4620,"votos":8,"candidato":"Paul Carrasco","value":0.16},{"id":5190,"votos":53,"candidato":"Paul Carrasco","value":0.17},{"id":5495,"votos":6,"candidato":"Paul Carrasco","value":0.18}]