[{"id":935,"votos":23,"candidato":"Ximena Peña","value":1.24},{"id":950,"votos":15,"candidato":"Ximena Peña","value":1.14},{"id":1335,"votos":17,"candidato":"Ximena Peña","value":1.42},{"id":1410,"votos":26,"candidato":"Ximena Peña","value":1.67},{"id":1605,"votos":35,"candidato":"Ximena Peña","value":1.31},{"id":1725,"votos":44,"candidato":"Ximena Peña","value":1.16},{"id":1775,"votos":6,"candidato":"Ximena Peña","value":1.21},{"id":1895,"votos":5,"candidato":"Ximena Peña","value":0.31},{"id":1900,"votos":7,"candidato":"Ximena Peña","value":0.76},{"id":3305,"votos":7,"candidato":"Ximena Peña","value":0.62},{"id":4345,"votos":11,"candidato":"Ximena Peña","value":1.14},{"id":5160,"votos":93,"candidato":"Ximena Peña","value":0.66}]