[{"id":95,"votos":3013,"candidato":"Guillermo Lasso","value":25.07},{"id":125,"votos":4024,"candidato":"Guillermo Lasso","value":25.61},{"id":385,"votos":15136,"candidato":"Guillermo Lasso","value":29.29},{"id":390,"votos":753487,"candidato":"Guillermo Lasso","value":52.39},{"id":395,"votos":9701,"candidato":"Guillermo Lasso","value":26.09},{"id":400,"votos":42250,"candidato":"Guillermo Lasso","value":46.53},{"id":415,"votos":12212,"candidato":"Guillermo Lasso","value":34.63},{"id":420,"votos":46288,"candidato":"Guillermo Lasso","value":41.25},{"id":425,"votos":28047,"candidato":"Guillermo Lasso","value":57.49},{"id":430,"votos":13903,"candidato":"Guillermo Lasso","value":36.32},{"id":435,"votos":12011,"candidato":"Guillermo Lasso","value":28.31},{"id":505,"votos":11036,"candidato":"Guillermo Lasso","value":33.58},{"id":510,"votos":7173,"candidato":"Guillermo Lasso","value":28.61},{"id":675,"votos":3186,"candidato":"Guillermo Lasso","value":29.78},{"id":715,"votos":10259,"candidato":"Guillermo Lasso","value":33.19},{"id":735,"votos":13191,"candidato":"Guillermo Lasso","value":42.59},{"id":790,"votos":5929,"candidato":"Guillermo Lasso","value":39.97},{"id":820,"votos":59964,"candidato":"Guillermo Lasso","value":41.56},{"id":835,"votos":5433,"candidato":"Guillermo Lasso","value":34.15},{"id":870,"votos":8299,"candidato":"Guillermo Lasso","value":32.44},{"id":890,"votos":2435,"candidato":"Guillermo Lasso","value":30.62},{"id":920,"votos":4237,"candidato":"Guillermo Lasso","value":36.11},{"id":940,"votos":4641,"candidato":"Guillermo Lasso","value":34.16},{"id":985,"votos":3551,"candidato":"Guillermo Lasso","value":46.82},{"id":986,"votos":1739,"candidato":"Guillermo Lasso","value":21.42}]