[
    {
        "id": 285,
        "votos": 7592,
        "candidato": "Yaku Perez",
        "value": 47.67
    },
    {
        "id": 730,
        "votos": 3076,
        "candidato": "Yaku Perez",
        "value": 75.65
    },
    {
        "id": 845,
        "votos": 356,
        "candidato": "Yaku Perez",
        "value": 49.17
    },
    {
        "id": 860,
        "votos": 912,
        "candidato": "Yaku Perez",
        "value": 57.83
    },
    {
        "id": 905,
        "votos": 1533,
        "candidato": "Yaku Perez",
        "value": 58.83
    },
    {
        "id": 2255,
        "votos": 1388,
        "candidato": "Yaku Perez",
        "value": 51.22
    },
    {
        "id": 2430,
        "votos": 1665,
        "candidato": "Yaku Perez",
        "value": 38.89
    },
    {
        "id": 2570,
        "votos": 1897,
        "candidato": "Yaku Perez",
        "value": 54.03
    },
    {
        "id": 2595,
        "votos": 600,
        "candidato": "Yaku Perez",
        "value": 51.11
    },
    {
        "id": 2680,
        "votos": 1809,
        "candidato": "Yaku Perez",
        "value": 57.23
    },
    {
        "id": 3105,
        "votos": 2731,
        "candidato": "Yaku Perez",
        "value": 69.54
    },
    {
        "id": 3165,
        "votos": 4984,
        "candidato": "Yaku Perez",
        "value": 40.74
    },
    {
        "id": 3460,
        "votos": 3094,
        "candidato": "Yaku Perez",
        "value": 49.56
    },
    {
        "id": 3685,
        "votos": 2305,
        "candidato": "Yaku Perez",
        "value": 61.27
    },
    {
        "id": 3795,
        "votos": 3591,
        "candidato": "Yaku Perez",
        "value": 45.14
    },
    {
        "id": 3850,
        "votos": 1071,
        "candidato": "Yaku Perez",
        "value": 46.36
    },
    {
        "id": 3870,
        "votos": 3702,
        "candidato": "Yaku Perez",
        "value": 55.28
    },
    {
        "id": 3980,
        "votos": 4262,
        "candidato": "Yaku Perez",
        "value": 66.27
    },
    {
        "id": 4095,
        "votos": 2544,
        "candidato": "Yaku Perez",
        "value": 56.87
    },
    {
        "id": 4200,
        "votos": 6719,
        "candidato": "Yaku Perez",
        "value": 57.90
    },
    {
        "id": 4225,
        "votos": 2060,
        "candidato": "Yaku Perez",
        "value": 69.06
    },
    {
        "id": 10150,
        "votos": 63355,
        "candidato": "Yaku Perez",
        "value": 30.48
    }



]