[{"id":105,"votos":73,"candidato":"Isidro Romero","value":4.05},{"id":560,"votos":25,"candidato":"Isidro Romero","value":2.61},{"id":1115,"votos":58,"candidato":"Isidro Romero","value":1.81},{"id":1880,"votos":21,"candidato":"Isidro Romero","value":1.71},{"id":2810,"votos":74,"candidato":"Isidro Romero","value":2.90},{"id":2990,"votos":52,"candidato":"Isidro Romero","value":2.48},{"id":4490,"votos":11,"candidato":"Isidro Romero","value":1.35},{"id":5485,"votos":738,"candidato":"Isidro Romero","value":3.21},{"id":7465,"votos":156,"candidato":"Isidro Romero","value":4.28},{"id":7470,"votos":68,"candidato":"Isidro Romero","value":3.46},{"id":7475,"votos":220,"candidato":"Isidro Romero","value":3.88}]