[{"id":95,"votos":1087,"candidato":"Guillermo Lasso","value":9.22},{"id":125,"votos":1437,"candidato":"Guillermo Lasso","value":9.94},{"id":385,"votos":6166,"candidato":"Guillermo Lasso","value":12.87},{"id":390,"votos":409372,"candidato":"Guillermo Lasso","value":29.24},{"id":395,"votos":4756,"candidato":"Guillermo Lasso","value":13.44},{"id":400,"votos":23040,"candidato":"Guillermo Lasso","value":26.25},{"id":415,"votos":4984,"candidato":"Guillermo Lasso","value":15.13},{"id":420,"votos":19407,"candidato":"Guillermo Lasso","value":17.71},{"id":425,"votos":23346,"candidato":"Guillermo Lasso","value":49.18},{"id":430,"votos":5176,"candidato":"Guillermo Lasso","value":14.60},{"id":435,"votos":4435,"candidato":"Guillermo Lasso","value":10.65},{"id":505,"votos":4018,"candidato":"Guillermo Lasso","value":12.25},{"id":510,"votos":2499,"candidato":"Guillermo Lasso","value":10.02},{"id":675,"votos":1206,"candidato":"Guillermo Lasso","value":12.02},{"id":715,"votos":4353,"candidato":"Guillermo Lasso","value":14.83},{"id":735,"votos":6255,"candidato":"Guillermo Lasso","value":20.08},{"id":790,"votos":2694,"candidato":"Guillermo Lasso","value":19.10},{"id":820,"votos":28152,"candidato":"Guillermo Lasso","value":19.93},{"id":835,"votos":2423,"candidato":"Guillermo Lasso","value":16.32},{"id":870,"votos":3019,"candidato":"Guillermo Lasso","value":12.50},{"id":890,"votos":1102,"candidato":"Guillermo Lasso","value":13.91},{"id":920,"votos":1823,"candidato":"Guillermo Lasso","value":16.47},{"id":940,"votos":2190,"candidato":"Guillermo Lasso","value":16.58},{"id":985,"votos":1032,"candidato":"Guillermo Lasso","value":13.07},{"id":986,"votos":718,"candidato":"Guillermo Lasso","value":9.17}]