[
    {
        "id": 1075,
        "votos": 0,
        "candidato": "Gerson Almeida",
        "value": 0.00
    },
    {
        "id": 1080,
        "votos": 6,
        "candidato": "Gerson Almeida",
        "value": 0.97
    },
    {
        "id": 1100,
        "votos": 0,
        "candidato": "Gerson Almeida",
        "value": 0.00
    },
    {
        "id": 6335,
        "votos": 11,
        "candidato": "Gerson Almeida",
        "value": 0.60
    },
    {
        "id": 6950,
        "votos": 1,
        "candidato": "Gerson Almeida",
        "value": 0.22
    }
]