[{"id":70,"votos":3,"candidato":"Pedro Freile","value":0.52},{"id":110,"votos":2,"candidato":"Pedro Freile","value":0.24},{"id":435,"votos":0,"candidato":"Pedro Freile","value":0.00},{"id":535,"votos":4,"candidato":"Pedro Freile","value":0.50},{"id":570,"votos":1,"candidato":"Pedro Freile","value":0.59},{"id":620,"votos":10,"candidato":"Pedro Freile","value":1.24},{"id":2395,"votos":6,"candidato":"Pedro Freile","value":0.96},{"id":3455,"votos":4,"candidato":"Pedro Freile","value":1.02},{"id":3725,"votos":2,"candidato":"Pedro Freile","value":0.25},{"id":3955,"votos":9,"candidato":"Pedro Freile","value":1.00},{"id":4075,"votos":9,"candidato":"Pedro Freile","value":0.85},{"id":4125,"votos":9,"candidato":"Pedro Freile","value":1.81},{"id":6130,"votos":85,"candidato":"Pedro Freile","value":0.72}]