[{"candidato2":"Andres Arauz","candidato1":"Guillermo Lasso","id":230,"votos":738,"votos1":304,"fill":"#EF8A62","votos2":434,"porcentaje1":41.19,"porcentaje2":58.81},{"candidato2":"Andres Arauz","candidato1":"Guillermo Lasso","id":1090,"votos":1985,"votos1":807,"fill":"#EF8A62","votos2":1178,"porcentaje1":40.65,"porcentaje2":59.35},{"candidato2":"Andres Arauz","candidato1":"Guillermo Lasso","id":3615,"votos":711,"votos1":140,"fill":"#EF8A62","votos2":571,"porcentaje1":19.69,"porcentaje2":80.31},{"candidato2":"Andres Arauz","candidato1":"Guillermo Lasso","id":6300,"votos":2100,"votos1":956,"fill":"#EF8A62","votos2":1144,"porcentaje1":45.52,"porcentaje2":54.48}]