[{"id":55,"votos":46,"candidato":"Isidro Romero","value":0.76},{"id":60,"votos":35,"candidato":"Isidro Romero","value":0.82},{"id":650,"votos":21,"candidato":"Isidro Romero","value":1.32},{"id":755,"votos":80,"candidato":"Isidro Romero","value":0.82},{"id":850,"votos":4,"candidato":"Isidro Romero","value":0.40},{"id":3960,"votos":39,"candidato":"Isidro Romero","value":0.59},{"id":4155,"votos":17,"candidato":"Isidro Romero","value":0.63},{"id":5620,"votos":162,"candidato":"Isidro Romero","value":0.70}]