[{"id":75,"votos":13,"candidato":"Giovanny Andrade","value":0.23},{"id":305,"votos":15,"candidato":"Giovanny Andrade","value":0.32},{"id":1755,"votos":10,"candidato":"Giovanny Andrade","value":0.23},{"id":1970,"votos":22,"candidato":"Giovanny Andrade","value":0.33},{"id":1990,"votos":17,"candidato":"Giovanny Andrade","value":0.54},{"id":2045,"votos":9,"candidato":"Giovanny Andrade","value":0.35},{"id":4440,"votos":18,"candidato":"Giovanny Andrade","value":0.30},{"id":5730,"votos":58,"candidato":"Giovanny Andrade","value":0.21},{"id":5860,"votos":65,"candidato":"Giovanny Andrade","value":0.16},{"id":5865,"votos":88,"candidato":"Giovanny Andrade","value":0.19},{"id":5870,"votos":14,"candidato":"Giovanny Andrade","value":0.21},{"id":6065,"votos":85,"candidato":"Giovanny Andrade","value":0.18},{"id":6175,"votos":58,"candidato":"Giovanny Andrade","value":0.19},{"id":6180,"votos":4,"candidato":"Giovanny Andrade","value":0.06}]