[{"candidato2":"Andres Arauz","candidato1":"Guillermo Lasso","id":55,"votos":4754,"votos1":3136,"fill":"#045A8D","votos2":1618,"porcentaje1":65.97,"porcentaje2":34.03},{"candidato2":"Andres Arauz","candidato1":"Guillermo Lasso","id":60,"votos":3253,"votos1":2081,"fill":"#045A8D","votos2":1172,"porcentaje1":63.97,"porcentaje2":36.03},{"candidato2":"Andres Arauz","candidato1":"Guillermo Lasso","id":650,"votos":1449,"votos1":765,"fill":"#045A8D","votos2":684,"porcentaje1":52.80,"porcentaje2":47.20},{"candidato2":"Andres Arauz","candidato1":"Guillermo Lasso","id":755,"votos":8063,"votos1":3865,"fill":"#EF8A62","votos2":4198,"porcentaje1":47.94,"porcentaje2":52.06},{"candidato2":"Andres Arauz","candidato1":"Guillermo Lasso","id":850,"votos":669,"votos1":390,"fill":"#045A8D","votos2":279,"porcentaje1":58.30,"porcentaje2":41.70},{"candidato2":"Andres Arauz","candidato1":"Guillermo Lasso","id":3960,"votos":5361,"votos1":3267,"fill":"#045A8D","votos2":2094,"porcentaje1":60.94,"porcentaje2":39.06},{"candidato2":"Andres Arauz","candidato1":"Guillermo Lasso","id":4155,"votos":2470,"votos1":1706,"fill":"#045A8D","votos2":764,"porcentaje1":69.07,"porcentaje2":30.93},{"candidato2":"Andres Arauz","candidato1":"Guillermo Lasso","id":5620,"votos":18995,"votos1":12878,"fill":"#045A8D","votos2":6117,"porcentaje1":67.80,"porcentaje2":32.20}]