[{"id":165,"votos":18,"candidato":"Juan Velasco","value":0.57},{"id":480,"votos":22,"candidato":"Juan Velasco","value":0.25},{"id":2600,"votos":23,"candidato":"Juan Velasco","value":0.50},{"id":2635,"votos":4,"candidato":"Juan Velasco","value":0.22},{"id":3735,"votos":7,"candidato":"Juan Velasco","value":0.29},{"id":4620,"votos":39,"candidato":"Juan Velasco","value":0.76},{"id":5190,"votos":212,"candidato":"Juan Velasco","value":0.68},{"id":5495,"votos":16,"candidato":"Juan Velasco","value":0.49}]