[{"id":450,"votos":182,"candidato":"Yaku Perez","value":12.73},{"id":655,"votos":117,"candidato":"Yaku Perez","value":13.45},{"id":895,"votos":404,"candidato":"Yaku Perez","value":21.26},{"id":2320,"votos":264,"candidato":"Yaku Perez","value":23.47},{"id":3570,"votos":409,"candidato":"Yaku Perez","value":13.75},{"id":3930,"votos":182,"candidato":"Yaku Perez","value":12.53},{"id":3940,"votos":220,"candidato":"Yaku Perez","value":8.80},{"id":4240,"votos":688,"candidato":"Yaku Perez","value":11.29},{"id":5205,"votos":1705,"candidato":"Yaku Perez","value":10.84},{"id":5210,"votos":3432,"candidato":"Yaku Perez","value":12.24},{"id":5335,"votos":3307,"candidato":"Yaku Perez","value":11.23},{"id":5600,"votos":566,"candidato":"Yaku Perez","value":9.34},{"id":6905,"votos":1511,"candidato":"Yaku Perez","value":11.67}]